{
  "applications": "*",
  "changelogDate": "20230917185415",
  "dto": "no",
  "embedded": false,
  "entityTableName": "customer",
  "fields": [
    {
      "fieldName": "name",
      "fieldType": "String",
      "fieldValidateRules": ["required"]
    },
    {
      "fieldName": "email",
      "fieldType": "String",
      "fieldValidateRules": ["required"]
    },
    {
      "fieldName": "address",
      "fieldType": "String"
    },
    {
      "fieldName": "phone",
      "fieldType": "String"
    }
  ],
  "fluentMethods": true,
  "jpaMetamodelFiltering": false,
  "name": "Customer",
  "pagination": "no",
  "readOnly": false,
  "relationships": [
    {
      "otherEntityName": "order",
      "otherEntityRelationshipName": "customer",
      "relationshipName": "orders",
      "relationshipType": "many-to-one"
    }
  ],
  "service": "no"
}
